Metadata-Version: 1.0
Name: beginning
Version: 0.1.0
Summary: Basic utils for Python.
Home-page: https://github.com/ycyuxin/beginning
Author: ycyuxin
Author-email: ycyuxin@qq.com
License: UNKNOWN
Platform: UNKNOWN
